thumbor_text_filter/__init__.py
thumbor_text_filter/text.py
thumbor_text_filter-0.0.2.dist-info/DESCRIPTION.rst
thumbor_text_filter-0.0.2.dist-info/METADATA
thumbor_text_filter-0.0.2.dist-info/RECORD
thumbor_text_filter-0.0.2.dist-info/WHEEL
thumbor_text_filter-0.0.2.dist-info/metadata.json
thumbor_text_filter-0.0.2.dist-info/top_level.txt
